mail_sender.py
python_mail_sender-0.1.4.dist-info/LICENSE
python_mail_sender-0.1.4.dist-info/METADATA
python_mail_sender-0.1.4.dist-info/WHEEL
python_mail_sender-0.1.4.dist-info/top_level.txt
python_mail_sender-0.1.4.dist-info/RECORD
