Metadata-Version: 2.1
Name: python-mail-sender
Version: 0.1.4
Summary: Mail Sender Module that helps you send your emails perfectly.
Home-page: https://github.com/mansy996/mail_sender
Author: Ahmed Mansy
License: MIT
Platform: UNKNOWN
Classifier: Programming Language :: Python :: 3
Classifier: License :: OSI Approved :: MIT License
Classifier: Operating System :: OS Independent
Requires-Python: >=3.6
License-File: LICENSE
